kdenlive_api/__init__.py
kdenlive_api/asset.py
kdenlive_api/bin.py
kdenlive_api/client.py
kdenlive_api/composition.py
kdenlive_api/effects.py
kdenlive_api/exceptions.py
kdenlive_api/project.py
kdenlive_api/py.typed
kdenlive_api/render.py
kdenlive_api/timeline.py
kdenlive_api/transition.py
kdenlive_api/types.py
kdenlive_api/validators.py
kdenlive_api-0.2.1.dist-info/METADATA
kdenlive_api-0.2.1.dist-info/WHEEL
kdenlive_api-0.2.1.dist-info/licenses/LICENSE
kdenlive_api-0.2.1.dist-info/RECORD
